codebot_tools/__init__.py
codebot_tools/basic.py
codebot_tools/botcore.py
codebot_tools-0.0.3.1.dist-info/METADATA
codebot_tools-0.0.3.1.dist-info/WHEEL
codebot_tools-0.0.3.1.dist-info/licenses/LICENSE
codebot_tools-0.0.3.1.dist-info/RECORD
