Metadata-Version: 2.4
Name: codebot_tools
Version: 0.0.3.1
Summary: Basic complementary tools to simplify the development of programs for CodeBot.
Author-email: Neptune25 <example@example.com>
License-Expression: CC-BY-NC-ND-4.0
License-File: LICENSE
Classifier: Operating System :: OS Independent
Classifier: Programming Language :: Python :: 3
Requires-Python: >=3.9
Requires-Dist: alive-progress
Requires-Dist: build
Requires-Dist: hatchling
Requires-Dist: manimgl
Requires-Dist: twine
